petlib/__init__.py
petlib/_compat.py
petlib/_petlib.abi3.so
petlib/bindings.py
petlib/bn.py
petlib/cipher.py
petlib/compile.py
petlib/ec.py
petlib/ecdsa.py
petlib/hmac.py
petlib/pack.py
petlib/_cffi_src/install_openssl_v1_1.sh
petlib/_cffi_src/openssl/openssl_v1_0.c
petlib/_cffi_src/openssl/openssl_v1_0.h
petlib/_cffi_src/openssl/openssl_v1_1.c
petlib/_cffi_src/openssl/openssl_v1_1.h
petlib_fork-0.0.45.dist-info/LICENSE.txt
petlib_fork-0.0.45.dist-info/METADATA
petlib_fork-0.0.45.dist-info/WHEEL
petlib_fork-0.0.45.dist-info/top_level.txt
petlib_fork-0.0.45.dist-info/RECORD
