Metadata-Version: 2.1
Name: petlib-fork
Version: 0.0.45
Summary: A library implementing a number of Privacy Enhancing Technologies (PETs)
Home-page: https://pypi.python.org/pypi/petlib/
Author: George Danezis
Author-email: g.danezis@ucl.ac.uk
License: 2-clause BSD
License-File: LICENSE.txt
Requires-Dist: cffi (>=1.0.0)
Requires-Dist: pycparser (>=2.10)
Requires-Dist: future (>=0.14.3)
Requires-Dist: pytest (>=2.5.0)
Requires-Dist: pytest-cov (>=1.8.1)
Requires-Dist: msgpack (>=1.0.4)
